LICENSE.txt
MANIFEST.in
README.md
pyproject.toml
fasta/__init__.py
fasta/aligned.py
fasta/common.py
fasta/core.py
fasta/exceptions.py
fasta/fastq.py
fasta/fastqc.py
fasta/graphs.py
fasta/indexed.py
fasta/paired.py
fasta/primers.py
fasta/qual.py
fasta/sizes.py
fasta/splitable.py
fasta/sra.py
fasta/validator.py
fasta.egg-info/PKG-INFO
fasta.egg-info/SOURCES.txt
fasta.egg-info/dependency_links.txt
fasta.egg-info/requires.txt
fasta.egg-info/top_level.txt
fasta/tests/pytest.ini
fasta/tests/test_counting.py
fasta/tests/test_validation.py
fasta/tests/test_write.py
fasta/tests/data/invalid.fastq
fasta/tests/data/seqs.fastq
fasta/tests/data/seqs.fastq.gz