Metadata-Version: 2.4
Name: fasta
Version: 2.3.3
Summary: The fasta python package enables you to deal with biological sequence files easily.
Author-email: Lucas Sinclair <lucas.sinclair@me.com>
License: Copyright (c) 2026 Lucas Sinclair
Project-URL: Homepage, http://github.com/xapple/fasta/
Keywords: fasta,fastq,bioinformatics,dna,sequences
Classifier: License :: OSI Approved :: MIT License
Classifier: Operating System :: OS Independent
Classifier: Topic :: Scientific/Engineering :: Bio-Informatics
Requires-Python: >=3.8
License-File: LICENSE.txt
Requires-Dist: autopaths>=1.6.2
Requires-Dist: plumbing>=2.11.3
Requires-Dist: biopython
Requires-Dist: tqdm
Requires-Dist: sh
Provides-Extra: graphs
Requires-Dist: numpy; extra == "graphs"
Requires-Dist: matplotlib; extra == "graphs"
Provides-Extra: primers
Requires-Dist: regex; extra == "primers"
Dynamic: license-file
